[
	{
		"id": "traceability",
		"title": "Traceability",
		"description": "Traceability",
		"submodules": [
			"serialparttypization",
			"assemblypartrelationship",
			"batch",
			"partasplanned",
			"singlelevelbomasplanned",
			"singlelevelusageasbuilt",
			"partsiteinformationasplanned"
		]
	},
	{
		"id": "circulareconomy",
		"title": "Circular Economy",
		"description": "Circular Economy",
		"submodules": [
			"serialparttypization",
			"assemblypartrelationship",
			"batch"
		]
	},
	{
		"id": "quality",
		"title": "Quality",
		"description": "Quality",
		"submodules": [
			"serialparttypization",
			"assemblypartrelationship",
			"batch",
			"singlelevelusageasbuilt"
		]
	},
	{
		"id": "sustainability",
		"title": "Sustainability",
		"description": "Sustainability",
		"submodules": [
			"partasplanned",
			"partsiteinformationasplanned",
			"singlelevelbomasplanned",
			"singlelevelusageasplanned"
		]
	}
]